[
  {
    "id": "service_counter_basic",
    "name": "Service Counter",
    "category": "counter",
    "allowed_rooms": ["sales_room"],
    "footprint": {"width": 2, "height": 1},
    "rotation": {"allowed": true, "increments_degrees": 90},
    "tags": ["customer_facing", "service_counter"],
    "blocks_movement": true,
    "interaction_sides": ["front", "back"],
    "cost": 90,
    "purchase_price": 90,
    "unlock_level": 1,
    "effects": {"cashier_efficiency_bonus": 0.05}
  },
  {
    "id": "small_table_two_seat",
    "name": "Two-Seat Table",
    "category": "seating",
    "allowed_rooms": ["sales_room"],
    "footprint": {"width": 2, "height": 2},
    "rotation": {"allowed": true, "increments_degrees": 90},
    "tags": ["customer_seating", "seating"],
    "blocks_movement": true,
    "interaction_sides": ["front", "back", "left", "right"],
    "cost": 75,
    "purchase_price": 75,
    "unlock_level": 1,
    "effects": {"dine_in_capacity": 2, "patience_bonus": 0.02}
  },
  {
    "id": "decor_wall_menu",
    "name": "Wall Menu",
    "category": "decor",
    "allowed_rooms": ["sales_room"],
    "footprint": {"width": 1, "height": 1},
    "rotation": {"allowed": true, "increments_degrees": 90},
    "tags": ["decor", "wall_attached"],
    "blocks_movement": false,
    "interaction_sides": [],
    "cost": 45,
    "purchase_price": 45,
    "unlock_level": 1,
    "effects": {"customer_choice_speed_bonus": 0.04}
  },
  {
    "id": "ingredient_crate_stack",
    "name": "Ingredient Crate Stack",
    "category": "storage",
    "allowed_rooms": ["warehouse"],
    "footprint": {"width": 1, "height": 1},
    "rotation": {"allowed": true, "increments_degrees": 90},
    "tags": ["storage", "warehouse_intake", "tablet_delivery_target"],
    "blocks_movement": true,
    "interaction_sides": ["front"],
    "cost": 35,
    "purchase_price": 35,
    "unlock_level": 1,
    "effects": {"raw_storage_slots": 4}
  },
  {
    "id": "utility_shelf",
    "name": "Utility Shelf",
    "category": "storage",
    "allowed_rooms": ["warehouse"],
    "footprint": {"width": 1, "height": 2},
    "rotation": {"allowed": true, "increments_degrees": 90},
    "tags": ["storage", "utility_shelf", "utility"],
    "blocks_movement": true,
    "interaction_sides": ["front"],
    "cost": 50,
    "purchase_price": 50,
    "unlock_level": 1,
    "effects": {"utility_storage_slots": 6}
  },
  {
    "id": "kitchen_pass_counter",
    "name": "Kitchen Pass Counter",
    "category": "counter",
    "allowed_rooms": ["kitchen", "sales_room"],
    "footprint": {"width": 2, "height": 1},
    "rotation": {"allowed": true, "increments_degrees": 90},
    "tags": ["service_counter", "short_term_storage", "worker_station"],
    "blocks_movement": true,
    "interaction_sides": ["front", "back"],
    "cost": 110,
    "purchase_price": 110,
    "unlock_level": 1,
    "effects": {"finished_handoff_slots": 4}
  }
]
